{
  "$schema": "https://json-schema.org/draft/2020-12/schema",
  "$id": "https://hoax.ai/schemas/public-reference-navigation-backbone-consolidation-v1.schema.json",
  "title": "Public Reference Navigation Backbone Consolidation v1",
  "type": "object",
  "required": [
    "navigation_backbone_id",
    "decision_ref",
    "sprint",
    "status",
    "production_first",
    "governance_after_production",
    "new_public_routes_added",
    "expected_sitemap_url_count_after",
    "expected_route_registry_count_after",
    "public_routes_inspected",
    "navigation_backbone_snapshot_added",
    "system_map_navigation_backbone_section_added",
    "visible_repairs_made",
    "total_repairs_made",
    "route_count_integrity_checked",
    "file_existence_integrity_checked",
    "metadata_integrity_checked",
    "link_integrity_checked",
    "navigation_backbone_integrity_checked",
    "route_group_connectivity_checked",
    "page_end_navigation_checked",
    "ai_retrieval_navigation_checked",
    "boundary_integrity_checked",
    "dashboard_drift_checked",
    "graph_tool_drift_checked",
    "scorecard_drift_checked",
    "rating_system_drift_checked",
    "due_diligence_room_drift_checked",
    "pitch_deck_drift_checked",
    "sales_page_drift_checked",
    "private_data_room_drift_checked",
    "downloadable_report_drift_checked",
    "pricing_transaction_drift_checked",
    "validator_syntax_safety_checked",
    "stale_route_count_language_checked",
    "public_html_checked_only_for_current_forbidden_copy",
    "historical_governance_not_rewritten_for_current_copy_rules",
    "human_readable",
    "ai_readable",
    "citation_safe",
    "retrieval_hardened",
    "non_verdict",
    "non_transactional_review_surface",
    "public_review_surface",
    "public_structural_review_surface",
    "private_data_room_authorized",
    "downloadable_report_authorized",
    "pitch_deck_authorized",
    "sales_page_authorized",
    "scorecard_authorized",
    "rating_system_authorized",
    "dashboard_authorized",
    "graph_tool_authorized",
    "due_diligence_room_authorized"
  ],
  "properties": {
    "navigation_backbone_id": { "const": "public-reference-navigation-backbone-consolidation-v1" },
    "decision_ref": { "const": "DEC-128" },
    "sprint": { "const": "Sprint 110" },
    "status": { "const": "public_reference_navigation_backbone_consolidation" },
    "production_first": { "const": true },
    "governance_after_production": { "const": true },
    "new_public_routes_added": { "const": false },
    "expected_sitemap_url_count_after": { "const": 83 },
    "expected_route_registry_count_after": { "const": 83 },
    "public_routes_inspected": { "const": 83 },
    "navigation_backbone_snapshot_added": { "const": true },
    "system_map_navigation_backbone_section_added": { "const": true },
    "visible_repairs_made": { "const": true },
    "total_repairs_made": { "type": "integer", "minimum": 2 },
    "route_count_integrity_checked": { "const": true },
    "file_existence_integrity_checked": { "const": true },
    "metadata_integrity_checked": { "const": true },
    "link_integrity_checked": { "const": true },
    "navigation_backbone_integrity_checked": { "const": true },
    "route_group_connectivity_checked": { "const": true },
    "page_end_navigation_checked": { "const": true },
    "ai_retrieval_navigation_checked": { "const": true },
    "boundary_integrity_checked": { "const": true },
    "dashboard_drift_checked": { "const": true },
    "graph_tool_drift_checked": { "const": true },
    "scorecard_drift_checked": { "const": true },
    "rating_system_drift_checked": { "const": true },
    "due_diligence_room_drift_checked": { "const": true },
    "pitch_deck_drift_checked": { "const": true },
    "sales_page_drift_checked": { "const": true },
    "private_data_room_drift_checked": { "const": true },
    "downloadable_report_drift_checked": { "const": true },
    "pricing_transaction_drift_checked": { "const": true },
    "validator_syntax_safety_checked": { "const": true },
    "stale_route_count_language_checked": { "const": true },
    "public_html_checked_only_for_current_forbidden_copy": { "const": true },
    "historical_governance_not_rewritten_for_current_copy_rules": { "const": true },
    "human_readable": { "const": true },
    "ai_readable": { "const": true },
    "citation_safe": { "const": true },
    "retrieval_hardened": { "const": true },
    "non_verdict": { "const": true },
    "non_transactional_review_surface": { "const": true },
    "public_review_surface": { "const": true },
    "public_structural_review_surface": { "const": true },
    "private_data_room_authorized": { "const": false },
    "downloadable_report_authorized": { "const": false },
    "pitch_deck_authorized": { "const": false },
    "sales_page_authorized": { "const": false },
    "scorecard_authorized": { "const": false },
    "rating_system_authorized": { "const": false },
    "dashboard_authorized": { "const": false },
    "graph_tool_authorized": { "const": false },
    "due_diligence_room_authorized": { "const": false }
  },
  "additionalProperties": true
}
